.svnignore
LICENSE
README
setup.cfg
setup.py
examples/generator.py
examples/hcalendar.py
examples/links.py
examples/load.py
examples/lots.py
examples/pylucene.py
feeds/bryn.rss
feeds/bug.rss
feeds/charlvn.rss
feeds/fooz.rss
feeds/highvoltage.rss
feeds/johann.rss
feeds/nlt.rss
feeds/ourmedia.rss
feeds/rss2.0.xml
feeds/thezashow.rss
feeds/vhata.rss
pyaggregator/__init__.py
pyaggregator/aggregator.py
pyaggregator/elixirsupport.py
pyaggregator/standalone.py
pyaggregator.egg-info/PKG-INFO
pyaggregator.egg-info/SOURCES.txt
pyaggregator.egg-info/dependency_links.txt
pyaggregator.egg-info/entry_points.txt
pyaggregator.egg-info/not-zip-safe
pyaggregator.egg-info/paster_plugins.txt
pyaggregator.egg-info/top_level.txt
