Metadata-Version: 1.0
Name: pyaggregator
Version: 0.3
Summary: Handles the tedious portions of aggregating web log posts
Home-page: UNKNOWN
Author: Neil Blakey-Milner
Author-email: nbm@nxsy.org
License: MIT
Keywords: blog rss atom feed
Platform: UNKNOWN
Classifier: Development Status :: 3 - Alpha
Classifier: License :: OSI Approved :: MIT License
Classifier: Operating System :: POSIX
Classifier: Programming Language :: Python
